README.txt
setup.cfg
setup.py
Chandler_XmppPlugin.egg-info/PKG-INFO
Chandler_XmppPlugin.egg-info/SOURCES.txt
Chandler_XmppPlugin.egg-info/dependency_links.txt
Chandler_XmppPlugin.egg-info/entry_points.txt
Chandler_XmppPlugin.egg-info/top_level.txt
chandler_xmpp/__init__.py
chandler_xmpp/tests/__init__.py
