Metadata-Version: 1.0
Name: Chandler-XmppPlugin
Version: 0.8-r1761
Summary: XMPP support for Chandler
Home-page: UNKNOWN
Author: Morgen Sagen
Author-email: UNKNOWN
License: UNKNOWN
Platform: UNKNOWN
Classifier: Development Status :: 3 - Alpha
Classifier: Environment :: Plugins
Classifier: Framework :: Chandler
Classifier: Intended Audience :: Developers
Classifier: License :: OSI Approved :: Apache Software License
Classifier: Operating System :: OS Independent
Classifier: Programming Language :: Python
Classifier: Topic :: Office/Business :: Groupware
